{"name":"loginTest","id":"testcases.LoginTest:loginTest","scenarioId":"testcases.LoginTest:loginTest","testCaseName":"testcases.LoginTest","methodName":"loginTest","testSteps":[{"number":1,"description":"Performing Login","duration":8384,"startTime":"2024-12-31T12:33:17.285528300-05:00[America/Guayaquil]","screenshots":[{"screenshot":"9bd91f487dce10bfa320b8b402b2759c6e860f885afa9ddb2f5189def52ddcf1.png","timeStamp":1735666405669,"screenshotName":"9bd91f487dce10bfa320b8b402b2759c6e860f885afa9ddb2f5189def52ddcf1.png"}],"result":"SUCCESS","precondition":false,"level":0},{"number":2,"description":"Entering Password","duration":5677,"startTime":"2024-12-31T12:33:25.670636300-05:00[America/Guayaquil]","screenshots":[{"screenshot":"1691d9c0d330d2f47e5a292b5161b9634cabd06c7a2dd16feb72af7cb8769107.png","timeStamp":1735666406289,"screenshotName":"1691d9c0d330d2f47e5a292b5161b9634cabd06c7a2dd16feb72af7cb8769107.png"},{"screenshot":"baf4e12ca07ccb42ca5aa039bfffa22220073781195c60e93ebe889595980cef.png","timeStamp":1735666411347,"screenshotName":"baf4e12ca07ccb42ca5aa039bfffa22220073781195c60e93ebe889595980cef.png"}],"result":"SUCCESS","precondition":false,"level":0}],"userStory":{"id":"testcases.LoginTest","storyName":"LoginTest","displayName":"LoginTest","storyClassName":"testcases.LoginTest","path":"testcases.LoginTest","pathElements":[{"name":"testcases","description":"testcases"},{"name":"LoginTest","description":"LoginTest"}],"narrative":"","type":"feature"},"title":"Executing Login Test","tags":[{"name":"Chrome","type":"context","displayName":"Chrome"},{"name":"Windows","type":"context","displayName":"Windows"},{"name":"Chrome, Windows","type":"context","displayName":"Chrome, Windows"}],"startTime":"2024-12-31T12:33:16.818263-05:00[America/Guayaquil]","endTime":"2024-12-31T12:33:31.352399600-05:00[America/Guayaquil]","duration":8434,"projectKey":"","sessionId":"f4cb0f0a2bd6a9336b8af116ceb950b7","driver":"chrome","isManualTestingUpToDate":false,"context":"chrome,windows","manual":false,"testSource":"JUnit","order":0,"result":"SUCCESS"}